residuum/__init__.py
residuum/_molecule.py
residuum/_proforma.py
residuum/_psimod.py
residuum/_smiles.py
residuum/exceptions.py
residuum-0.1.0a2.dist-info/WHEEL
residuum-0.1.0a2.dist-info/METADATA
residuum-0.1.0a2.dist-info/RECORD
